dyno/__init__.py
dyno/bijectors.py
dyno/copulas.py
dyno/data.py
dyno/distributions.py
dyno/filtering.py
dyno/finite_differences.py
dyno/fitting.py
dyno/linalg.py
dyno/math.py
dyno/parameter.py
dyno/pricing.py
dyno/state_space_model.py
dyno/structural_time_series.py
dyno/util.py
dyno/viz.py
quantbet_dyno-0.29.5.dist-info/METADATA
quantbet_dyno-0.29.5.dist-info/WHEEL
quantbet_dyno-0.29.5.dist-info/top_level.txt
quantbet_dyno-0.29.5.dist-info/RECORD
