Metadata-Version: 2.1
Name: quantbet-dyno
Version: 0.29.5
Summary: QB dynamic models
Home-page: https://quant-nginx02.quantbet.co.uk:8001/projects/GEN/repos/dyno
Author: QB
License: UNKNOWN
Platform: UNKNOWN
Requires-Python: >=3.9
Requires-Dist: matplotlib (==3.5.1)
Requires-Dist: numpy (==1.22.3)
Requires-Dist: pandas (==1.4.2)
Requires-Dist: pyarrow (==7.0.0)
Requires-Dist: tensorflow (==2.8.0)
Requires-Dist: tensorflow-probability (==0.16.0)
